bobzillapypi-0.2.1.dist-info/METADATA
bobzillapypi-0.2.1.dist-info/WHEEL
bobzillapypi-0.2.1.dist-info/license_files/LICENSE-APACHE
bobzillapypi-0.2.1.dist-info/license_files/LICENSE-MIT
bobzillapypi.libs/libgcc_s-d7088d38.so.1
bobzillapypi/__init__.py
bobzillapypi/bobzillapypi.abi3.so
bobzillapypi-0.2.1.dist-info/RECORD
