Metadata-Version: 2.1
Name: bobzillapypi
Version: 0.2.1
Classifier: Development Status :: 3 - Alpha
Classifier: Intended Audience :: Developers
Classifier: License :: OSI Approved :: MIT License
Classifier: Operating System :: POSIX
Classifier: Operating System :: Microsoft :: Windows
Classifier: Operating System :: MacOS :: MacOS X
Classifier: Topic :: Utilities
Classifier: Programming Language :: Python
Classifier: Programming Language :: Python :: 3
Classifier: Programming Language :: Python :: 3 :: Only
Classifier: Programming Language :: Python :: 3.7
Classifier: Programming Language :: Python :: 3.8
Classifier: Programming Language :: Python :: 3.9
Classifier: Programming Language :: Python :: 3.10
Classifier: Programming Language :: Python :: 3.11
Classifier: Topic :: System :: Networking
Classifier: Topic :: System :: Networking :: Firewalls
License-File: LICENSE-APACHE
License-File: LICENSE-MIT
Summary: The ngrok Agent SDK for Python
Keywords: ngrok,python,pypi,pyo3,ingress,networking
License: MIT OR Apache-2.0
Requires-Python: >=3.7
Project-URL: repository, https://github.com/ngrok/ngrok-py
Project-URL: changelog, https://github.com/ngrok/ngrok-py/blob/main/CHANGELOG.md
Project-URL: homepage, https://ngrok.com
